<?xml version="1.0" encoding="utf-8"?>
<cms.contentitem>
  <ContentItemChannelID>
    <CodeName>Goldfinch</CodeName>
    <GUID>8d6b2e28-87c3-4ea4-8a3d-dfff7c209710</GUID>
    <ObjectType>cms.channel</ObjectType>
  </ContentItemChannelID>
  <ContentItemContentTypeID>
    <CodeName>Goldfinch.BlogPost</CodeName>
    <GUID>c3495cd5-11e9-4fca-a6be-85123e9e4b6e</GUID>
    <ObjectType>cms.contenttype</ObjectType>
  </ContentItemContentTypeID>
  <ContentItemGUID>66b13255-c2f0-4953-88f7-53bee54e64b8</ContentItemGUID>
  <ContentItemIsReusable>False</ContentItemIsReusable>
  <ContentItemIsSecured>False</ContentItemIsSecured>
  <ContentItemName>
    <![CDATA[RevolutionisingDigitalExperience_AYearOfXperienceByKenticoAndWhat_sNext-fedszw2j]]>
  </ContentItemName>
</cms.contentitem>